{
  "populationType": {
    "_DEFAULT": "Person"
  },
  "measurement": {
    "_DEFAULT": {
      "measuredProperty": "count",
      "statType": "measuredValue"
    },
    "Median age (years)": {
      "measuredProperty": "age",
      "statType": "medianValue",
      "unit": "Years"
    },
    "Median earnings (dollars)": {
      "measuredProperty": "earnings",
      "statType": "medianValue",
      "unit": "USDollar",
      "incomeStatus": "WithEarnings"
    },
    "Median earnings (dollars):": {
      "measuredProperty": "earnings",
      "statType": "medianValue",
      "unit": "USDollar",
      "incomeStatus": "WithEarnings"
    },
    "Mean earnings (dollars)": {
      "measuredProperty": "earnings",
      "statType": "meanValue",
      "unit": "USDollar",
      "incomeStatus": "WithEarnings"
    },
    "Mean earnings (dollars):": {
      "measuredProperty": "earnings",
      "statType": "meanValue",
      "unit": "USDollar",
      "incomeStatus": "WithEarnings"
    }
  },
  "enumSpecializations": {},
  "pvs": {
    "statType": {
      "Margin of Error": "marginOfError"
    },
    "age": {
      "Under 15 years": "[- 15 Years]",
      "15 to 17 years": "[15 17 Years]",
      "Under 18 years": "[- 18 Years]",
      "18 to 24 years": "[18 24 Years]",
      "25 to 34 years": "[25 34 Years]",
      "35 to 44 years": "[35 44 Years]",
      "45 to 54 years": "[45 54 Years]",
      "55 to 64 years": "[55 64 Years]",
      "65 to 74 years": "[65 74 Years]",
      "75 to 84 years": "[75 84 Years]",
      "65 years and over": "[65 - Years]",
      "85 years and over": "[85 - Years]",
      "Population 1 year and over": "[1 - Years]",
      "Population 5 years and over": "[5 - Years]",
      "Population 25 years and over": "[25 - Years]",
      "Population 15 years and over": "[15 - Years]",
      "Population 16 years and over": "[16 - Years]",
      "Population 18 to 64 years": "[18 64 Years]",
      "Population 65 years and over": "[65 - Years]",
      "Civilian population 18 years and over": "[18 - Years]",
      "Civilian employed population 16 years and over": "[16 - Years]"
    },
    "gender": {
      "Male": "Male",
      "Female": "Female"
    },
    "race": {
      "One race": "OneRace",
      "Two or more races": "TwoOrMoreRaces",
      "Hispanic or Latino (of any race)": "HispanicOrLatino",
      "White alone, not Hispanic or Latino": "WhiteAloneNotHispanicOrLatino",
      "White": "WhiteAlone",
      "Black or African American": "BlackOrAfricanAmericanAlone",
      "American Indian and Alaska Native": "AmericanIndianOrAlaskaNativeAlone",
      "Asian": "AsianAlone",
      "Native Hawaiian and Other Pacific Islander": "NativeHawaiianOrOtherPacificIslanderAlone",
      "Some other race": "SomeOtherRaceAlone"
    },
    "citizenship": {
      "Naturalized U.S. citizen": "USCitizenByNaturalization",
      "Native": "USCitizenBornInTheUnitedStates",
      "Not a U.S. citizen": "NotAUSCitizen"
    },
    "nativity": {
      "Foreign born": "USC_ForeignBorn",
      "Native": "USC_Native"
    },
    "disabilityStatus": {
      "With a disability": "WithDisability",
      "No disability": "NoDisability"
    },
    "residentStatus": {
      "Same county": "DifferentHouseInSameCounty",
      "Different county": "DifferentHouseInDifferentCounty",
      "Same state": "DifferentHouseInDifferentCountySameState",
      "Different state": "DifferentHouseInDifferentCountyDifferentState",
      "Abroad": "DifferentHouseAbroad",
      "Different address in the United States": "DifferentHouseInTheUS",
      "Same address": "SameHouse1YearAgo"
    },
    "educationalAttainment": {
      "Bachelor's degree or higher": "BachelorsDegreeOrHigher",
      "High school graduate or higher": "HighSchoolGraduateOrHigher"
    },
    "employmentStatus": {
      "In labor force": "BLS_InLaborForce",
      "Civilian labor force": "BLS_InLaborForce",
      "Not in labor force": "BLS_NotInLaborForce"
    },
    "employment": {
      "Employed": "BLS_Employed",
      "Civilian employed population 16 years and over": "BLS_Employed",
      "Unemployed": "BLS_Unemployed",
      "Not in labor force": "BLS_Unemployed"
    },
    "occupation": {
      "Management, business, science, and arts occupations": "SOCv2018/highLevelAggregation-1",
      "Service occupations": "SOCv2018/highLevelAggregation-2",
      "Sales and office occupations": "SOCv2018/highLevelAggregation-3",
      "Natural resources, construction, extraction, and maintenance occupations": "SOCv2018/highLevelAggregation-4",
      "Production, transportation, and material moving occupations": "SOCv2018/highLevelAggregation-5"
    },
    "maritalStatus": {
      "Widowed": "Widowed",
      "Never married": "NeverMarried",
      "Now married, except separated": "MarriedAndNotSeparated",
      "Separated": "Separated",
      "Divorced": "Divorced"
    },
    "schoolEnrollment XXXXX": {
      "Population 3 years and over enrolled in school": "EnrolledInSchool",
      "Nursery school through 12th grade": "XXXXXEnrolledInSchool"
    },
    "collegeOrGraduateSchoolEnrollment XXXXX": {
      "College or graduate school": "EnrolledInCollegeOrGraduateSchool"
    },
    "veteranStatus": {
      "Civilian veteran": "Veteran"
    },
    "languageSpokenAtHome": {
      "English only": "OnlyEnglish",
      "Language other than English": "LanguageOtherThanEnglish"
    },
    "armedForcesStatus": {
      "Civilian population 18 years and over": "Civilian",
      "Civilian employed population 16 years and over": "Civilian",
      "Civilian labor force": "Civilian",
      "Armed Forces": "InArmedForces",
      "Civilian veteran": "Civilian"
    },
    "abilityToSpeakEnglish": {
      "Speak English less than very well\"\"": "SpeakEnglishLessThanVeryWell"
    },
    "benefitsStatus": {
      "With Food Stamp/SNAP benefits": "WithFoodStampsInThePast12Months"
    },
    "incomeStatus": {
      "With earnings": "WithEarnings",
      "With earnings:": "WithEarnings"
    },
    "residentType": {
      "Total group quarters population": "GroupQuarters",
      "Total group quarters population MOE": "GroupQuarters",
      "Adult correctional facilities": "AdultCorrectionalFacilities",
      "Adult correctional facilities MOE": "AdultCorrectionalFacilities",
      "Nursing facilities/skilled nursing facilities": "NursingFacilities",
      "Nursing facilities/skilled nursing facilities MOE": "NursingFacilities",
      "College/university housing": "CollegeOrUniversityStudentHousing",
      "College/university housing MOE": "CollegeOrUniversityStudentHousing",
      "Juvenile Facilities": "JuvenileFacilities",
      "Juvenile Facilities MOE": "JuvenileFacilities",
      "Military quarters/military ships": "MilitaryQuartersOrMilitaryShips",
      "Military quarters/military ships MOE": "MilitaryQuartersOrMilitaryShips"
    },
    "placeOfBirth": {
      "Europe": "europe",
      "Asia": "asia"
    },
    "dateOfEntry": {
      "Entered before 2000": "[- 2000 Date]",
      "Entered 2000 to 2009": "[2000 2009 Date]",
      "Entered 2010 or later": "[2010 - Date]"
      

    }
  },
  "inferredSpec": {},
  "universePVs": [
    {
      "populationType": "Person",
      "constraintProperties": ["maritalStatus"],
      "dependentPVs": {
        "age": "[15 - Years]"
      }
    },
    {
      "populationType": "Person",
      "constraintProperties": ["employmentStatus"],
      "dependentPVs": {
        "age": "[16 - Years]"
      }
    },
    {
      "populationType": "Person",
      "constraintProperties": ["employment"],
      "dependentPVs": {
        "age": "[16 - Years]",
        "employmentStatus": "BLS_InLaborForce"
      }
    },
    {
      "populationType": "Person",
      "constraintProperties": ["educationalAttainment"],
      "dependentPVs": {
        "age": "[25 - Years]"
      }
    },
    {
      "populationType": "Person",
      "constraintProperties": ["schoolEnrollment"],
      "dependentPVs": {
        "age": "[3 - Years]"
      }
    },
    {
      "populationType": "Person",
      "constraintProperties": ["detailedLevelOfSchool"],
      "dependentPVs": {
        "age": "[3 - Years]"
      }
    },
    {
      "populationType": "Person",
      "constraintProperties": ["veteranStatus"],
      "dependentPVs": {
        "age": "[18 - Years]",
        "armedForcesStatus": "Civilian"
      }
    },
    {
      "populationType": "Person",
      "constraintProperties": ["armedForcesStatus"],
      "dependentPVs": {
        "age": "[16 - Years]",
        "employmentStatus": "BLS_InLaborForce"
      }
    },
    {
      "populationType": "Person",
      "constraintProperties": ["languageSpokenAtHome"],
      "dependentPVs": {
        "age": "[5 - Years]"
      }
    },
    {
      "populationType": "Person",
      "constraintProperties": ["abilityToSpeakEnglish"],
      "dependentPVs": {
        "age": "[5 - Years]",
        "languageSpokenAtHome": "LanguageOtherThanEnglish"
      }
    },
    {
      "populationType": "Person",
      "constraintProperties": ["residentStatus"],
      "dependentPVs": {
        "age": "[1 - Years]"
      }
    },
    {
      "populationType": "Person",
      "constraintProperties": ["citizenship"],
      "dependentPVs": {
        "age": "[15 - Years]"
      }
    },
    {
      "populationType": "Person",
      "constraintProperties": ["placeOfBirth"],
      "dependentPVs": {
        "nativity": "USC_ForeignBorn"
      }
    },
    {
      "populationType": "Person",
      "constraintProperties": ["occupation"],
      "dependentPVs": {
        "age": "[16 - Years]",
        "armedForcesStatus": "Civilian",
        "employment": "BLS_Employed"
      }
    }
  ],
  "denominators": {},
  "ignoreColumns": [
    "id",
    "Geographic Area Name",
    "Per capita income (dollars)",
    "Percent of civilian labor force"
  ],
  "ignoreTokens": [
    "DISABILITY STATUS",
    "Estimate",
    "OCCUPATION",
    "MARITAL STATUS",
    "EDUCATIONAL ATTAINMENT",
    "LANGUAGE SPOKEN AT HOME AND ABILITY TO SPEAK ENGLISH",
    "WORLD REGION OF BIRTH OF FOREIGN BORN",
    "SCHOOL ENROLLMENT",
    "EMPLOYMENT STATUS",
    "INCOME AND BENEFITS IN THE PAST 12 MONTHS (IN 2019 INFLATION-ADJUSTED DOLLARS)",
    "INCOME AND BENEFITS IN THE PAST 12 MONTHS (IN 2018 INFLATION-ADJUSTED DOLLARS)",
    "RESIDENCE 1 YEAR AGO",
    "PLACE OF BIRTH, NATIVITY AND CITIZENSHIP STATUS, AND YEAR OF ENTRY",
    "SEX AND AGE",
    "RACE AND HISPANIC ORIGIN OR LATINO ORIGIN",
    "VETERAN STATUS"


  ]
}